entities_python/__init__.py
entities_python/_base_client.py
entities_python/_client.py
entities_python/_compat.py
entities_python/_constants.py
entities_python/_exceptions.py
entities_python/_files.py
entities_python/_models.py
entities_python/_qs.py
entities_python/_resource.py
entities_python/_response.py
entities_python/_streaming.py
entities_python/_types.py
entities_python/_version.py
entities_python/py.typed
entities_python/_utils/__init__.py
entities_python/_utils/_logs.py
entities_python/_utils/_proxy.py
entities_python/_utils/_reflection.py
entities_python/_utils/_resources_proxy.py
entities_python/_utils/_streams.py
entities_python/_utils/_sync.py
entities_python/_utils/_transform.py
entities_python/_utils/_typing.py
entities_python/_utils/_utils.py
entities_python/lib/.keep
entities_python/resources/__init__.py
entities_python/resources/cloud/__init__.py
entities_python/resources/cloud/cloud.py
entities_python/resources/cloud/identities.py
entities_python/resources/cloud/runtimes.py
entities_python/resources/memory/__init__.py
entities_python/resources/memory/drm_instances.py
entities_python/resources/memory/memory.py
entities_python/resources/orgs/__init__.py
entities_python/resources/orgs/api_keys.py
entities_python/resources/orgs/organizations.py
entities_python/resources/orgs/orgs.py
entities_python/resources/toolbox/__init__.py
entities_python/resources/toolbox/adapters.py
entities_python/resources/toolbox/toolbox.py
entities_python/resources/toolbox/tools.py
entities_python/types/__init__.py
entities_python/types/cloud/__init__.py
entities_python/types/cloud/identity.py
entities_python/types/cloud/identity_create_params.py
entities_python/types/cloud/identity_list_response.py
entities_python/types/cloud/identity_update_params.py
entities_python/types/cloud/runtime.py
entities_python/types/cloud/runtime_create_params.py
entities_python/types/cloud/runtime_list_response.py
entities_python/types/cloud/runtime_update_params.py
entities_python-0.1.0a17.dist-info/METADATA
entities_python-0.1.0a17.dist-info/WHEEL
entities_python-0.1.0a17.dist-info/licenses/LICENSE
entities_python-0.1.0a17.dist-info/RECORD
